{"v": "5.5.7", "fr": 30, "ip": 0, "op": 180, "w": 400, "h": 400, "nm": "Birthday Cake Celebration", "ddd": 0, "layers": [{"ty": 4, "nm": "Frosting", "ip": 0, "op": 180, "st": 0, "ks": {"p": {"k": [200, 280, 0]}}, "shapes": [{"ty": "gr", "it": [{"ty": "rc", "s": {"k": [160, 10]}, "p": {"k": [0, -5]}}, {"ty": "el", "s": {"k": [20, 20]}, "p": {"k": [-60, 0]}}, {"ty": "el", "s": {"k": [20, 30]}, "p": {"k": [-20, 5]}}, {"ty": "el", "s": {"k": [20, 25]}, "p": {"k": [30, 0]}}, {"ty": "el", "s": {"k": [20, 20]}, "p": {"k": [65, -5]}}, {"ty": "fl", "c": {"k": [1, 1, 1, 1]}}]}]}, {"ty": 4, "nm": "Cake_Bottom", "ip": 0, "op": 180, "st": 0, "ks": {"o": {"a": 0, "k": 100}, "p": {"a": 0, "k": [200, 310, 0]}, "s": {"a": 0, "k": [100, 100, 100]}}, "shapes": [{"ty": "gr", "it": [{"ty": "rc", "s": {"a": 0, "k": [160, 70]}, "p": {"a": 0, "k": [0, 0]}, "r": {"a": 0, "k": 10}}, {"ty": "fl", "c": {"a": 0, "k": [1, 0.84, 0, 1]}}]}]}, {"ty": 4, "nm": "Cake_Top", "ip": 0, "op": 180, "st": 0, "ks": {"o": {"a": 0, "k": 100}, "p": {"a": 0, "k": [200, 245, 0]}, "s": {"a": 0, "k": [100, 100, 100]}}, "shapes": [{"ty": "gr", "it": [{"ty": "rc", "s": {"a": 0, "k": [100, 60]}, "p": {"a": 0, "k": [0, 0]}, "r": {"a": 0, "k": 8}}, {"ty": "fl", "c": {"a": 0, "k": [1, 0.41, 0.7, 1]}}]}]}, {"ty": 4, "nm": "Candle", "ip": 0, "op": 180, "st": 0, "ks": {"o": {"a": 0, "k": 100}, "p": {"a": 0, "k": [200, 200, 0]}, "s": {"a": 0, "k": [100, 100, 100]}}, "shapes": [{"ty": "gr", "it": [{"ty": "rc", "s": {"a": 0, "k": [10, 40]}, "p": {"a": 0, "k": [0, 0]}, "r": {"a": 0, "k": 2}}, {"ty": "fl", "c": {"a": 0, "k": [1, 1, 1, 1]}}]}]}, {"ty": 4, "nm": "Flame", "ip": 0, "op": 90, "st": 0, "ks": {"o": {"a": 0, "k": 100}, "p": {"a": 0, "k": [200, 175, 0]}, "s": {"a": 1, "k": [{"t": 0, "s": [110, 110, 100]}, {"t": 5, "s": [90, 90, 100]}, {"t": 10, "s": [110, 110, 100]}, {"t": 15, "s": [90, 90, 100]}, {"t": 20, "s": [110, 110, 100]}, {"t": 25, "s": [90, 90, 100]}, {"t": 30, "s": [110, 110, 100]}, {"t": 35, "s": [90, 90, 100]}, {"t": 40, "s": [110, 110, 100]}, {"t": 45, "s": [90, 90, 100]}, {"t": 50, "s": [110, 110, 100]}, {"t": 55, "s": [90, 90, 100]}, {"t": 60, "s": [110, 110, 100]}, {"t": 65, "s": [90, 90, 100]}, {"t": 70, "s": [110, 110, 100]}, {"t": 75, "s": [90, 90, 100]}, {"t": 80, "s": [110, 110, 100]}, {"t": 85, "s": [90, 90, 100]}, {"t": 90, "s": [0, 0, 100]}]}, "a": {"k": [0, 15, 0]}}, "shapes": [{"ty": "gr", "it": [{"ty": "el", "s": {"a": 0, "k": [20, 30]}, "p": {"a": 0, "k": [0, 0]}}, {"ty": "fl", "c": {"a": 0, "k": [1, 0.65, 0, 1]}}]}]}, {"ty": 4, "nm": "Smoke", "ip": 90, "op": 180, "st": 0, "ks": {"o": {"a": 1, "k": [{"t": 90, "s": [0]}, {"t": 110, "s": [60]}, {"t": 150, "s": [0]}]}, "p": {"a": 1, "k": [{"t": 90, "s": [200, 170, 0]}, {"t": 150, "s": [210, 100, 0]}]}, "s": {"a": 1, "k": [{"t": 90, "s": [20, 20, 100]}, {"t": 150, "s": [100, 100, 100]}]}}, "shapes": [{"ty": "gr", "it": [{"ty": "el", "s": {"a": 0, "k": [40, 30]}, "p": {"a": 0, "k": [0, 0]}}, {"ty": "fl", "c": {"a": 0, "k": [1, 1, 1, 1]}}]}]}, {"ty": 4, "nm": "Sparkle_5", "ip": 0, "op": 180, "st": 0, "ks": {"o": {"a": 1, "k": [{"t": 0, "s": [0]}, {"t": 30, "s": [100]}, {"t": 60, "s": [0]}, {"t": 90, "s": [100]}, {"t": 120, "s": [0]}, {"t": 150, "s": [100]}, {"t": 180, "s": [0]}]}, "p": {"a": 0, "k": [250, 80, 0]}, "s": {"a": 0, "k": [100, 100, 100]}}, "shapes": [{"ty": "gr", "it": [{"ty": "sr", "sy": 1, "p": {"k": [0, 0]}, "pt": {"k": 4}, "r": {"k": 0}, "ir": {"k": 3}, "is": {"k": 0}, "or": {"k": 10}, "os": {"k": 0}}, {"ty": "fl", "c": {"a": 0, "k": [1, 1, 1, 1]}}]}]}, {"ty": 4, "nm": "Sparkle_4", "ip": 0, "op": 180, "st": 0, "ks": {"o": {"a": 1, "k": [{"t": 0, "s": [0]}, {"t": 30, "s": [100]}, {"t": 60, "s": [0]}, {"t": 90, "s": [100]}, {"t": 120, "s": [0]}, {"t": 150, "s": [100]}, {"t": 180, "s": [0]}]}, "p": {"a": 0, "k": [150, 100, 0]}, "s": {"a": 0, "k": [100, 100, 100]}}, "shapes": [{"ty": "gr", "it": [{"ty": "sr", "sy": 1, "p": {"k": [0, 0]}, "pt": {"k": 4}, "r": {"k": 0}, "ir": {"k": 3}, "is": {"k": 0}, "or": {"k": 10}, "os": {"k": 0}}, {"ty": "fl", "c": {"a": 0, "k": [1, 1, 1, 1]}}]}]}, {"ty": 4, "nm": "Sparkle_3", "ip": 0, "op": 180, "st": 0, "ks": {"o": {"a": 1, "k": [{"t": 0, "s": [0]}, {"t": 30, "s": [100]}, {"t": 60, "s": [0]}, {"t": 90, "s": [100]}, {"t": 120, "s": [0]}, {"t": 150, "s": [100]}, {"t": 180, "s": [0]}]}, "p": {"a": 0, "k": [320, 280, 0]}, "s": {"a": 0, "k": [100, 100, 100]}}, "shapes": [{"ty": "gr", "it": [{"ty": "sr", "sy": 1, "p": {"k": [0, 0]}, "pt": {"k": 4}, "r": {"k": 0}, "ir": {"k": 3}, "is": {"k": 0}, "or": {"k": 10}, "os": {"k": 0}}, {"ty": "fl", "c": {"a": 0, "k": [1, 1, 1, 1]}}]}]}, {"ty": 4, "nm": "Sparkle_2", "ip": 0, "op": 180, "st": 0, "ks": {"o": {"a": 1, "k": [{"t": 0, "s": [0]}, {"t": 30, "s": [100]}, {"t": 60, "s": [0]}, {"t": 90, "s": [100]}, {"t": 120, "s": [0]}, {"t": 150, "s": [100]}, {"t": 180, "s": [0]}]}, "p": {"a": 0, "k": [80, 250, 0]}, "s": {"a": 0, "k": [100, 100, 100]}}, "shapes": [{"ty": "gr", "it": [{"ty": "sr", "sy": 1, "p": {"k": [0, 0]}, "pt": {"k": 4}, "r": {"k": 0}, "ir": {"k": 3}, "is": {"k": 0}, "or": {"k": 10}, "os": {"k": 0}}, {"ty": "fl", "c": {"a": 0, "k": [1, 1, 1, 1]}}]}]}, {"ty": 4, "nm": "Sparkle_1", "ip": 0, "op": 180, "st": 0, "ks": {"o": {"a": 1, "k": [{"t": 0, "s": [0]}, {"t": 30, "s": [100]}, {"t": 60, "s": [0]}, {"t": 90, "s": [100]}, {"t": 120, "s": [0]}, {"t": 150, "s": [100]}, {"t": 180, "s": [0]}]}, "p": {"a": 0, "k": [300, 120, 0]}, "s": {"a": 0, "k": [100, 100, 100]}}, "shapes": [{"ty": "gr", "it": [{"ty": "sr", "sy": 1, "p": {"k": [0, 0]}, "pt": {"k": 4}, "r": {"k": 0}, "ir": {"k": 3}, "is": {"k": 0}, "or": {"k": 10}, "os": {"k": 0}}, {"ty": "fl", "c": {"a": 0, "k": [1, 1, 1, 1]}}]}]}, {"ty": 4, "nm": "Sparkle_0", "ip": 0, "op": 180, "st": 0, "ks": {"o": {"a": 1, "k": [{"t": 0, "s": [0]}, {"t": 30, "s": [100]}, {"t": 60, "s": [0]}, {"t": 90, "s": [100]}, {"t": 120, "s": [0]}, {"t": 150, "s": [100]}, {"t": 180, "s": [0]}]}, "p": {"a": 0, "k": [100, 150, 0]}, "s": {"a": 0, "k": [100, 100, 100]}}, "shapes": [{"ty": "gr", "it": [{"ty": "sr", "sy": 1, "p": {"k": [0, 0]}, "pt": {"k": 4}, "r": {"k": 0}, "ir": {"k": 3}, "is": {"k": 0}, "or": {"k": 10}, "os": {"k": 0}}, {"ty": "fl", "c": {"a": 0, "k": [1, 1, 1, 1]}}]}]}, {"ty": 4, "nm": "Confetti_24", "ip": 0, "op": 180, "st": 0, "ks": {"o": {"a": 0, "k": 100}, "p": {"a": 1, "k": [{"t": 0, "s": [329.5737196165984, -98.0, 0]}, {"t": 10, "s": [338.79887631185767, -69.13248654051871, 0]}, {"t": 20, "s": [346.51227193767966, -16.350341907227403, 0]}, {"t": 30, "s": [357.4656649071273, 52.0, 0]}, {"t": 40, "s": [378.502250468088, 132.94010767585027, 0]}, {"t": 50, "s": [388.44382629785105, 224.74861218395142, 0]}, {"t": 60, "s": [394.72375219778223, 326.26406871192853, 0]}, {"t": 70, "s": [405.00086119019176, 436.6338310781814, 0]}, {"t": 80, "s": [414.37694112613985, 555.1972647421808, 0]}, {"t": 90, "s": [415.09022902821835, 681.4228634059948, 0]}, {"t": 100, "s": [427.4885011778125, 814.870929175277, 0]}, {"t": 110, "s": [438.23656161631834, 955.1698185319719, 0]}, {"t": 120, "s": [445.1423675904601, 1102.0, 0]}, {"t": 130, "s": [448.41975823977936, 1255.0828996529863, 0]}, {"t": 140, "s": [460.9147274504048, 1414.172829628501, 0]}, {"t": 150, "s": [468.4775451787207, 1579.0509831248423, 0]}, {"t": 160, "s": [487.2594545628782, 1749.5208614068022, 0]}, {"t": 170, "s": [499.6866443771948, 1925.4047214204743, 0]}, {"t": 180, "s": [498.45856148429294, 2106.5407685048604, 0]}]}, "r": {"a": 1, "k": [{"t": 0, "s": [0.0]}, {"t": 20, "s": [119.41694856874807]}, {"t": 40, "s": [238.83389713749614]}, {"t": 60, "s": [358.2508457062442]}, {"t": 80, "s": [477.6677942749923]}, {"t": 100, "s": [597.0847428437404]}, {"t": 120, "s": [716.5016914124884]}, {"t": 140, "s": [835.9186399812365]}, {"t": 160, "s": [955.3355885499845]}, {"t": 180, "s": [1074.7525371187328]}]}, "s": {"a": 0, "k": [100, 100, 100]}}, "shapes": [{"ty": "gr", "it": [{"ty": "rc", "s": {"a": 0, "k": [8, 8]}, "p": {"a": 0, "k": [0, 0]}, "r": {"a": 0, "k": 2}}, {"ty": "fl", "c": {"a": 0, "k": [1, 1, 0, 1]}}]}]}, {"ty": 4, "nm": "Confetti_23", "ip": 0, "op": 180, "st": 0, "ks": {"o": {"a": 0, "k": 100}, "p": {"a": 1, "k": [{"t": 0, "s": [329.37103538012184, -27.0, 0]}, {"t": 10, "s": [344.5735393983023, 1.8675134594812839, 0]}, {"t": 20, "s": [342.303182629666, 54.6496580927726, 0]}, {"t": 30, "s": [354.21357791623404, 123.0, 0]}, {"t": 40, "s": [348.9109315585306, 203.94010767585027, 0]}, {"t": 50, "s": [347.4621197516968, 295.7486121839514, 0]}, {"t": 60, "s": [343.98148730702263, 397.26406871192853, 0]}, {"t": 70, "s": [358.6836407936779, 507.6338310781814, 0]}, {"t": 80, "s": [362.9664710787933, 626.1972647421808, 0]}, {"t": 90, "s": [363.5323225272873, 752.4228634059948, 0]}, {"t": 100, "s": [365.0052785316175, 885.870929175277, 0]}, {"t": 110, "s": [358.124178031485, 1026.169818531972, 0]}, {"t": 120, "s": [363.4572184431404, 1173.0, 0]}, {"t": 130, "s": [371.7134685371042, 1326.0828996529863, 0]}, {"t": 140, "s": [374.3132622406376, 1485.172829628501, 0]}, {"t": 150, "s": [378.7574673023678, 1650.0509831248423, 0]}, {"t": 160, "s": [372.2453274651232, 1820.5208614068022, 0]}, {"t": 170, "s": [376.79638733164904, 1996.4047214204743, 0]}, {"t": 180, "s": [386.77646989253424, 2177.5407685048604, 0]}]}, "r": {"a": 1, "k": [{"t": 0, "s": [0.0]}, {"t": 20, "s": [113.19916509461666]}, {"t": 40, "s": [226.39833018923332]}, {"t": 60, "s": [339.59749528385]}, {"t": 80, "s": [452.79666037846664]}, {"t": 100, "s": [565.9958254730833]}, {"t": 120, "s": [679.1949905677]}, {"t": 140, "s": [792.3941556623166]}, {"t": 160, "s": [905.5933207569333]}, {"t": 180, "s": [1018.79248585155]}]}, "s": {"a": 0, "k": [100, 100, 100]}}, "shapes": [{"ty": "gr", "it": [{"ty": "rc", "s": {"a": 0, "k": [8, 8]}, "p": {"a": 0, "k": [0, 0]}, "r": {"a": 0, "k": 2}}, {"ty": "fl", "c": {"a": 0, "k": [1, 1, 0, 1]}}]}]}, {"ty": 4, "nm": "Confetti_22", "ip": 0, "op": 180, "st": 0, "ks": {"o": {"a": 0, "k": 100}, "p": {"a": 1, "k": [{"t": 0, "s": [360.5174107087972, -114.0, 0]}, {"t": 10, "s": [358.3330885353317, -85.13248654051871, 0]}, {"t": 20, "s": [353.3894214874704, -32.3503419072274, 0]}, {"t": 30, "s": [330.7290209546882, 36.0, 0]}, {"t": 40, "s": [341.4875560177102, 116.94010767585027, 0]}, {"t": 50, "s": [319.51334711226673, 208.74861218395142, 0]}, {"t": 60, "s": [327.42943842898313, 310.26406871192853, 0]}, {"t": 70, "s": [312.58658657179393, 420.6338310781814, 0]}, {"t": 80, "s": [309.1129422270708, 539.1972647421808, 0]}, {"t": 90, "s": [315.0016215464397, 665.4228634059948, 0]}, {"t": 100, "s": [292.62436652347844, 798.870929175277, 0]}, {"t": 110, "s": [299.04331868657476, 939.1698185319719, 0]}, {"t": 120, "s": [295.1657559112753, 1086.0, 0]}, {"t": 130, "s": [276.4986115777406, 1239.0828996529863, 0]}, {"t": 140, "s": [280.5750141484108, 1398.172829628501, 0]}, {"t": 150, "s": [277.30006827856516, 1563.0509831248423, 0]}, {"t": 160, "s": [269.5917378648516, 1733.5208614068022, 0]}, {"t": 170, "s": [266.3751957270477, 1909.4047214204743, 0]}, {"t": 180, "s": [259.3380060339687, 2090.5407685048604, 0]}]}, "r": {"a": 1, "k": [{"t": 0, "s": [0.0]}, {"t": 20, "s": [189.7465139009571]}, {"t": 40, "s": [379.4930278019142]}, {"t": 60, "s": [569.2395417028713]}, {"t": 80, "s": [758.9860556038284]}, {"t": 100, "s": [948.7325695047854]}, {"t": 120, "s": [1138.4790834057426]}, {"t": 140, "s": [1328.2255973066997]}, {"t": 160, "s": [1517.9721112076568]}, {"t": 180, "s": [1707.7186251086137]}]}, "s": {"a": 0, "k": [100, 100, 100]}}, "shapes": [{"ty": "gr", "it": [{"ty": "rc", "s": {"a": 0, "k": [8, 8]}, "p": {"a": 0, "k": [0, 0]}, "r": {"a": 0, "k": 2}}, {"ty": "fl", "c": {"a": 0, "k": [1, 0, 1, 1]}}]}]}, {"ty": 4, "nm": "Confetti_21", "ip": 0, "op": 180, "st": 0, "ks": {"o": {"a": 0, "k": 100}, "p": {"a": 1, "k": [{"t": 0, "s": [202.77425285664796, -56.0, 0]}, {"t": 10, "s": [199.19713585964894, -27.132486540518716, 0]}, {"t": 20, "s": [202.27663426138108, 25.649658092772597, 0]}, {"t": 30, "s": [200.75013177792445, 94.0, 0]}, {"t": 40, "s": [186.50923163637572, 174.94010767585027, 0]}, {"t": 50, "s": [190.74057824681148, 266.7486121839514, 0]}, {"t": 60, "s": [185.7584809569245, 368.26406871192853, 0]}, {"t": 70, "s": [171.17564642384596, 478.6338310781814, 0]}, {"t": 80, "s": [181.4838786420269, 597.1972647421808, 0]}, {"t": 90, "s": [175.25190101227798, 723.4228634059948, 0]}, {"t": 100, "s": [171.1836553442094, 856.870929175277, 0]}, {"t": 110, "s": [165.66085476267583, 997.1698185319719, 0]}, {"t": 120, "s": [170.41960131388234, 1144.0, 0]}, {"t": 130, "s": [155.70834385191435, 1297.0828996529863, 0]}, {"t": 140, "s": [152.99415375711024, 1456.172829628501, 0]}, {"t": 150, "s": [140.96234332363352, 1621.0509831248423, 0]}, {"t": 160, "s": [138.37941891934076, 1791.5208614068022, 0]}, {"t": 170, "s": [137.49232020434656, 1967.4047214204743, 0]}, {"t": 180, "s": [128.75153804800402, 2148.5407685048604, 0]}]}, "r": {"a": 1, "k": [{"t": 0, "s": [0.0]}, {"t": 20, "s": [61.396019567238476]}, {"t": 40, "s": [122.79203913447695]}, {"t": 60, "s": [184.18805870171542]}, {"t": 80, "s": [245.5840782689539]}, {"t": 100, "s": [306.9800978361924]}, {"t": 120, "s": [368.37611740343084]}, {"t": 140, "s": [429.77213697066935]}, {"t": 160, "s": [491.1681565379078]}, {"t": 180, "s": [552.5641761051463]}]}, "s": {"a": 0, "k": [100, 100, 100]}}, "shapes": [{"ty": "gr", "it": [{"ty": "rc", "s": {"a": 0, "k": [8, 8]}, "p": {"a": 0, "k": [0, 0]}, "r": {"a": 0, "k": 2}}, {"ty": "fl", "c": {"a": 0, "k": [0, 1, 0, 1]}}]}]}, {"ty": 4, "nm": "Confetti_20", "ip": 0, "op": 180, "st": 0, "ks": {"o": {"a": 0, "k": 100}, "p": {"a": 1, "k": [{"t": 0, "s": [301.3666154806605, -183.0, 0]}, {"t": 10, "s": [310.5067758422865, -154.13248654051873, 0]}, {"t": 20, "s": [298.1326411737043, -101.3503419072274, 0]}, {"t": 30, "s": [319.3687549710057, -33.0, 0]}, {"t": 40, "s": [314.04226075748767, 47.94010767585027, 0]}, {"t": 50, "s": [318.95230648650283, 139.74861218395142, 0]}, {"t": 60, "s": [307.65869534107105, 241.26406871192853, 0]}, {"t": 70, "s": [311.8295359065512, 351.6338310781814, 0]}, {"t": 80, "s": [323.30168180987425, 470.1972647421808, 0]}, {"t": 90, "s": [323.1829684684207, 596.4228634059948, 0]}, {"t": 100, "s": [330.1229530468652, 729.870929175277, 0]}, {"t": 110, "s": [325.2225940029458, 870.1698185319719, 0]}, {"t": 120, "s": [324.4072475230597, 1017.0, 0]}, {"t": 130, "s": [340.35285625343835, 1170.0828996529863, 0]}, {"t": 140, "s": [334.04488697182336, 1329.172829628501, 0]}, {"t": 150, "s": [332.0196871449236, 1494.0509831248423, 0]}, {"t": 160, "s": [331.8664968434524, 1664.5208614068022, 0]}, {"t": 170, "s": [333.7727097833829, 1840.4047214204743, 0]}, {"t": 180, "s": [347.0268250065255, 2021.5407685048604, 0]}]}, "r": {"a": 1, "k": [{"t": 0, "s": [0.0]}, {"t": 20, "s": [198.08857056775182]}, {"t": 40, "s": [396.17714113550363]}, {"t": 60, "s": [594.2657117032554]}, {"t": 80, "s": [792.3542822710073]}, {"t": 100, "s": [990.4428528387591]}, {"t": 120, "s": [1188.5314234065108]}, {"t": 140, "s": [1386.6199939742628]}, {"t": 160, "s": [1584.7085645420145]}, {"t": 180, "s": [1782.7971351097663]}]}, "s": {"a": 0, "k": [100, 100, 100]}}, "shapes": [{"ty": "gr", "it": [{"ty": "rc", "s": {"a": 0, "k": [8, 8]}, "p": {"a": 0, "k": [0, 0]}, "r": {"a": 0, "k": 2}}, {"ty": "fl", "c": {"a": 0, "k": [1, 0, 1, 1]}}]}]}, {"ty": 4, "nm": "Confetti_19", "ip": 0, "op": 180, "st": 0, "ks": {"o": {"a": 0, "k": 100}, "p": {"a": 1, "k": [{"t": 0, "s": [276.50862534505114, -196.0, 0]}, {"t": 10, "s": [252.14348020374726, -167.13248654051873, 0]}, {"t": 20, "s": [256.4218875466231, -114.3503419072274, 0]}, {"t": 30, "s": [254.47215941590028, -46.0, 0]}, {"t": 40, "s": [247.15177054716213, 34.94010767585027, 0]}, {"t": 50, "s": [238.30393025142405, 126.74861218395142, 0]}, {"t": 60, "s": [221.96421097478188, 228.26406871192853, 0]}, {"t": 70, "s": [212.77215584018816, 338.6338310781814, 0]}, {"t": 80, "s": [202.36907411502895, 457.1972647421808, 0]}, {"t": 90, "s": [208.57319218858282, 583.4228634059948, 0]}, {"t": 100, "s": [193.02620025642628, 716.870929175277, 0]}, {"t": 110, "s": [195.79461475793545, 857.1698185319719, 0]}, {"t": 120, "s": [187.70198712464398, 1004.0, 0]}, {"t": 130, "s": [179.55430160208675, 1157.0828996529863, 0]}, {"t": 140, "s": [163.0070053590554, 1316.172829628501, 0]}, {"t": 150, "s": [152.9538695222094, 1481.0509831248423, 0]}, {"t": 160, "s": [144.95670433794774, 1651.5208614068022, 0]}, {"t": 170, "s": [141.37892883811583, 1827.4047214204743, 0]}, {"t": 180, "s": [128.17409381559287, 2008.5407685048604, 0]}]}, "r": {"a": 1, "k": [{"t": 0, "s": [0.0]}, {"t": 20, "s": [101.40713895925461]}, {"t": 40, "s": [202.81427791850922]}, {"t": 60, "s": [304.22141687776383]}, {"t": 80, "s": [405.62855583701844]}, {"t": 100, "s": [507.0356947962731]}, {"t": 120, "s": [608.4428337555277]}, {"t": 140, "s": [709.8499727147823]}, {"t": 160, "s": [811.2571116740369]}, {"t": 180, "s": [912.6642506332915]}]}, "s": {"a": 0, "k": [100, 100, 100]}}, "shapes": [{"ty": "gr", "it": [{"ty": "rc", "s": {"a": 0, "k": [8, 8]}, "p": {"a": 0, "k": [0, 0]}, "r": {"a": 0, "k": 2}}, {"ty": "fl", "c": {"a": 0, "k": [1, 0, 1, 1]}}]}]}, {"ty": 4, "nm": "Confetti_18", "ip": 0, "op": 180, "st": 0, "ks": {"o": {"a": 0, "k": 100}, "p": {"a": 1, "k": [{"t": 0, "s": [283.39034927943464, -130.0, 0]}, {"t": 10, "s": [298.15863085456283, -101.13248654051871, 0]}, {"t": 20, "s": [316.264440937044, -48.3503419072274, 0]}, {"t": 30, "s": [347.1399401173687, 20.0, 0]}, {"t": 40, "s": [350.3351687307301, 100.94010767585027, 0]}, {"t": 50, "s": [373.0397386763683, 192.74861218395142, 0]}, {"t": 60, "s": [381.52179939439054, 294.26406871192853, 0]}, {"t": 70, "s": [408.7520237433427, 404.6338310781814, 0]}, {"t": 80, "s": [415.3487322459952, 523.1972647421808, 0]}, {"t": 90, "s": [434.32839465047005, 649.4228634059948, 0]}, {"t": 100, "s": [465.0019919405558, 782.870929175277, 0]}, {"t": 110, "s": [480.91661997691295, 923.1698185319719, 0]}, {"t": 120, "s": [483.09438548371696, 1070.0, 0]}, {"t": 130, "s": [499.52246324642385, 1223.0828996529863, 0]}, {"t": 140, "s": [520.5707890119794, 1382.172829628501, 0]}, {"t": 150, "s": [542.2506151190652, 1547.0509831248423, 0]}, {"t": 160, "s": [549.9860994037703, 1717.5208614068022, 0]}, {"t": 170, "s": [568.086901671209, 1893.4047214204743, 0]}, {"t": 180, "s": [595.0154045219191, 2074.5407685048604, 0]}]}, "r": {"a": 1, "k": [{"t": 0, "s": [0.0]}, {"t": 20, "s": [47.51720519422296]}, {"t": 40, "s": [95.03441038844592]}, {"t": 60, "s": [142.5516155826689]}, {"t": 80, "s": [190.06882077689184]}, {"t": 100, "s": [237.5860259711148]}, {"t": 120, "s": [285.1032311653378]}, {"t": 140, "s": [332.6204363595607]}, {"t": 160, "s": [380.1376415537837]}, {"t": 180, "s": [427.65484674800666]}]}, "s": {"a": 0, "k": [100, 100, 100]}}, "shapes": [{"ty": "gr", "it": [{"ty": "rc", "s": {"a": 0, "k": [8, 8]}, "p": {"a": 0, "k": [0, 0]}, "r": {"a": 0, "k": 2}}, {"ty": "fl", "c": {"a": 0, "k": [1, 1, 0, 1]}}]}]}, {"ty": 4, "nm": "Confetti_17", "ip": 0, "op": 180, "st": 0, "ks": {"o": {"a": 0, "k": 100}, "p": {"a": 1, "k": [{"t": 0, "s": [246.46162196133616, -40.0, 0]}, {"t": 10, "s": [237.70657907640185, -11.132486540518716, 0]}, {"t": 20, "s": [224.95728941905202, 41.6496580927726, 0]}, {"t": 30, "s": [225.94973313548863, 110.0, 0]}, {"t": 40, "s": [215.2760887019067, 190.94010767585027, 0]}, {"t": 50, "s": [216.77103959466933, 282.7486121839514, 0]}, {"t": 60, "s": [214.3635451548883, 384.26406871192853, 0]}, {"t": 70, "s": [217.29009647386602, 494.6338310781814, 0]}, {"t": 80, "s": [204.02140857021155, 613.1972647421808, 0]}, {"t": 90, "s": [198.84075166050047, 739.4228634059948, 0]}, {"t": 100, "s": [204.64032585043032, 872.870929175277, 0]}, {"t": 110, "s": [202.88254827289924, 1013.1698185319719, 0]}, {"t": 120, "s": [188.46880725306175, 1160.0, 0]}, {"t": 130, "s": [196.7229714683157, 1313.0828996529863, 0]}, {"t": 140, "s": [189.33865605730148, 1472.172829628501, 0]}, {"t": 150, "s": [188.66131002829928, 1637.0509831248423, 0]}, {"t": 160, "s": [179.14202129423447, 1807.5208614068022, 0]}, {"t": 170, "s": [182.74448217516007, 1983.4047214204743, 0]}, {"t": 180, "s": [176.34360343896327, 2164.5407685048604, 0]}]}, "r": {"a": 1, "k": [{"t": 0, "s": [0.0]}, {"t": 20, "s": [184.57212483041923]}, {"t": 40, "s": [369.14424966083845]}, {"t": 60, "s": [553.7163744912576]}, {"t": 80, "s": [738.2884993216769]}, {"t": 100, "s": [922.8606241520961]}, {"t": 120, "s": [1107.4327489825152]}, {"t": 140, "s": [1292.0048738129344]}, {"t": 160, "s": [1476.5769986433538]}, {"t": 180, "s": [1661.149123473773]}]}, "s": {"a": 0, "k": [100, 100, 100]}}, "shapes": [{"ty": "gr", "it": [{"ty": "rc", "s": {"a": 0, "k": [8, 8]}, "p": {"a": 0, "k": [0, 0]}, "r": {"a": 0, "k": 2}}, {"ty": "fl", "c": {"a": 0, "k": [1, 0, 0, 1]}}]}]}, {"ty": 4, "nm": "Confetti_16", "ip": 0, "op": 180, "st": 0, "ks": {"o": {"a": 0, "k": 100}, "p": {"a": 1, "k": [{"t": 0, "s": [257.4947176396059, -197.0, 0]}, {"t": 10, "s": [287.9605452639164, -168.13248654051873, 0]}, {"t": 20, "s": [303.3948359029631, -115.3503419072274, 0]}, {"t": 30, "s": [307.71618794973904, -47.0, 0]}, {"t": 40, "s": [327.71764692788486, 33.94010767585027, 0]}, {"t": 50, "s": [341.60109558049584, 125.74861218395142, 0]}, {"t": 60, "s": [360.05807883897324, 227.26406871192853, 0]}, {"t": 70, "s": [365.24293264776065, 337.6338310781814, 0]}, {"t": 80, "s": [385.71991520084964, 456.1972647421808, 0]}, {"t": 90, "s": [405.43252842554983, 582.4228634059948, 0]}, {"t": 100, "s": [428.42019532914617, 715.870929175277, 0]}, {"t": 110, "s": [434.3099867465101, 856.1698185319719, 0]}, {"t": 120, "s": [447.815457145096, 1003.0, 0]}, {"t": 130, "s": [471.4975785261215, 1156.0828996529863, 0]}, {"t": 140, "s": [475.5867824543329, 1315.172829628501, 0]}, {"t": 150, "s": [496.9408677565544, 1480.0509831248423, 0]}, {"t": 160, "s": [512.1825975796386, 1650.5208614068022, 0]}, {"t": 170, "s": [537.393254870269, 1826.4047214204743, 0]}, {"t": 180, "s": [552.9315511681989, 2007.5407685048604, 0]}]}, "r": {"a": 1, "k": [{"t": 0, "s": [0.0]}, {"t": 20, "s": [126.90556428642827]}, {"t": 40, "s": [253.81112857285655]}, {"t": 60, "s": [380.7166928592848]}, {"t": 80, "s": [507.6222571457131]}, {"t": 100, "s": [634.5278214321413]}, {"t": 120, "s": [761.4333857185696]}, {"t": 140, "s": [888.3389500049979]}, {"t": 160, "s": [1015.2445142914262]}, {"t": 180, "s": [1142.1500785778544]}]}, "s": {"a": 0, "k": [100, 100, 100]}}, "shapes": [{"ty": "gr", "it": [{"ty": "rc", "s": {"a": 0, "k": [8, 8]}, "p": {"a": 0, "k": [0, 0]}, "r": {"a": 0, "k": 2}}, {"ty": "fl", "c": {"a": 0, "k": [0, 1, 0, 1]}}]}]}, {"ty": 4, "nm": "Confetti_15", "ip": 0, "op": 180, "st": 0, "ks": {"o": {"a": 0, "k": 100}, "p": {"a": 1, "k": [{"t": 0, "s": [305.6406786325405, -118.0, 0]}, {"t": 10, "s": [315.5754709569019, -89.13248654051871, 0]}, {"t": 20, "s": [317.27875436199344, -36.3503419072274, 0]}, {"t": 30, "s": [322.10612271826943, 32.0, 0]}, {"t": 40, "s": [333.5605002056905, 112.94010767585027, 0]}, {"t": 50, "s": [336.31851931914696, 204.74861218395142, 0]}, {"t": 60, "s": [339.4543460673537, 306.26406871192853, 0]}, {"t": 70, "s": [356.0851684324099, 416.6338310781814, 0]}, {"t": 80, "s": [364.72166063473094, 535.1972647421808, 0]}, {"t": 90, "s": [371.2186896128114, 661.4228634059948, 0]}, {"t": 100, "s": [361.6460378985103, 794.870929175277, 0]}, {"t": 110, "s": [373.5800418706476, 935.1698185319719, 0]}, {"t": 120, "s": [383.7337523469642, 1082.0, 0]}, {"t": 130, "s": [379.45256289258134, 1235.0828996529863, 0]}, {"t": 140, "s": [397.0978253548904, 1394.172829628501, 0]}, {"t": 150, "s": [400.0025384750063, 1559.0509831248423, 0]}, {"t": 160, "s": [405.3160113130061, 1729.5208614068022, 0]}, {"t": 170, "s": [418.39291857660254, 1905.4047214204743, 0]}, {"t": 180, "s": [420.4624567133987, 2086.5407685048604, 0]}]}, "r": {"a": 1, "k": [{"t": 0, "s": [0.0]}, {"t": 20, "s": [107.41366644372783]}, {"t": 40, "s": [214.82733288745567]}, {"t": 60, "s": [322.2409993311835]}, {"t": 80, "s": [429.65466577491134]}, {"t": 100, "s": [537.0683322186392]}, {"t": 120, "s": [644.481998662367]}, {"t": 140, "s": [751.8956651060948]}, {"t": 160, "s": [859.3093315498227]}, {"t": 180, "s": [966.7229979935505]}]}, "s": {"a": 0, "k": [100, 100, 100]}}, "shapes": [{"ty": "gr", "it": [{"ty": "rc", "s": {"a": 0, "k": [8, 8]}, "p": {"a": 0, "k": [0, 0]}, "r": {"a": 0, "k": 2}}, {"ty": "fl", "c": {"a": 0, "k": [0, 1, 0, 1]}}]}]}, {"ty": 4, "nm": "Confetti_14", "ip": 0, "op": 180, "st": 0, "ks": {"o": {"a": 0, "k": 100}, "p": {"a": 1, "k": [{"t": 0, "s": [206.4511254997358, -137.0, 0]}, {"t": 10, "s": [206.64997845190865, -108.13248654051871, 0]}, {"t": 20, "s": [196.4026128732323, -55.3503419072274, 0]}, {"t": 30, "s": [201.02455461493756, 13.0, 0]}, {"t": 40, "s": [203.4181134222047, 93.94010767585027, 0]}, {"t": 50, "s": [196.32197725262978, 185.74861218395142, 0]}, {"t": 60, "s": [198.5868441329534, 287.26406871192853, 0]}, {"t": 70, "s": [203.3454693417787, 397.6338310781814, 0]}, {"t": 80, "s": [200.71220317163713, 516.1972647421808, 0]}, {"t": 90, "s": [210.06308582044747, 642.4228634059948, 0]}, {"t": 100, "s": [199.32065204899638, 775.870929175277, 0]}, {"t": 110, "s": [210.24180147362907, 916.1698185319719, 0]}, {"t": 120, "s": [194.88931460177457, 1063.0, 0]}, {"t": 130, "s": [212.33887064919296, 1216.0828996529863, 0]}, {"t": 140, "s": [203.23558290690582, 1375.172829628501, 0]}, {"t": 150, "s": [195.10747629488708, 1540.0509831248423, 0]}, {"t": 160, "s": [198.55466211754754, 1710.5208614068022, 0]}, {"t": 170, "s": [208.38959534757072, 1886.4047214204743, 0]}, {"t": 180, "s": [202.00588872393627, 2067.5407685048604, 0]}]}, "r": {"a": 1, "k": [{"t": 0, "s": [0.0]}, {"t": 20, "s": [187.15821368691917]}, {"t": 40, "s": [374.31642737383834]}, {"t": 60, "s": [561.4746410607574]}, {"t": 80, "s": [748.6328547476767]}, {"t": 100, "s": [935.7910684345958]}, {"t": 120, "s": [1122.949282121515]}, {"t": 140, "s": [1310.1074958084341]}, {"t": 160, "s": [1497.2657094953533]}, {"t": 180, "s": [1684.4239231822723]}]}, "s": {"a": 0, "k": [100, 100, 100]}}, "shapes": [{"ty": "gr", "it": [{"ty": "rc", "s": {"a": 0, "k": [8, 8]}, "p": {"a": 0, "k": [0, 0]}, "r": {"a": 0, "k": 2}}, {"ty": "fl", "c": {"a": 0, "k": [0, 1, 0, 1]}}]}]}, {"ty": 4, "nm": "Confetti_13", "ip": 0, "op": 180, "st": 0, "ks": {"o": {"a": 0, "k": 100}, "p": {"a": 1, "k": [{"t": 0, "s": [205.21153020158732, -34.0, 0]}, {"t": 10, "s": [206.53436560943123, -5.132486540518716, 0]}, {"t": 20, "s": [220.79532282809757, 47.6496580927726, 0]}, {"t": 30, "s": [214.74013475744027, 116.0, 0]}, {"t": 40, "s": [224.37490482701534, 196.94010767585027, 0]}, {"t": 50, "s": [222.74058894157702, 288.7486121839514, 0]}, {"t": 60, "s": [242.26766288884065, 390.26406871192853, 0]}, {"t": 70, "s": [240.3498997553401, 500.6338310781814, 0]}, {"t": 80, "s": [237.7434632499584, 619.1972647421808, 0]}, {"t": 90, "s": [235.23576726408936, 745.4228634059948, 0]}, {"t": 100, "s": [256.90703539780384, 878.870929175277, 0]}, {"t": 110, "s": [245.79302646193108, 1019.1698185319719, 0]}, {"t": 120, "s": [250.74803261709724, 1166.0, 0]}, {"t": 130, "s": [260.85387992718825, 1319.0828996529863, 0]}, {"t": 140, "s": [257.53357600653834, 1478.172829628501, 0]}, {"t": 150, "s": [273.1617987286973, 1643.0509831248423, 0]}, {"t": 160, "s": [268.4700698810432, 1813.5208614068022, 0]}, {"t": 170, "s": [285.7692310949457, 1989.4047214204743, 0]}, {"t": 180, "s": [286.0838401520805, 2170.5407685048604, 0]}]}, "r": {"a": 1, "k": [{"t": 0, "s": [0.0]}, {"t": 20, "s": [168.89284074978278]}, {"t": 40, "s": [337.78568149956556]}, {"t": 60, "s": [506.67852224934836]}, {"t": 80, "s": [675.5713629991311]}, {"t": 100, "s": [844.4642037489139]}, {"t": 120, "s": [1013.3570444986967]}, {"t": 140, "s": [1182.2498852484794]}, {"t": 160, "s": [1351.1427259982622]}, {"t": 180, "s": [1520.035566748045]}]}, "s": {"a": 0, "k": [100, 100, 100]}}, "shapes": [{"ty": "gr", "it": [{"ty": "rc", "s": {"a": 0, "k": [8, 8]}, "p": {"a": 0, "k": [0, 0]}, "r": {"a": 0, "k": 2}}, {"ty": "fl", "c": {"a": 0, "k": [1, 1, 0, 1]}}]}]}, {"ty": 4, "nm": "Confetti_12", "ip": 0, "op": 180, "st": 0, "ks": {"o": {"a": 0, "k": 100}, "p": {"a": 1, "k": [{"t": 0, "s": [327.7272464692112, -57.0, 0]}, {"t": 10, "s": [327.79687031383486, -28.132486540518716, 0]}, {"t": 20, "s": [318.18575287750224, 24.649658092772597, 0]}, {"t": 30, "s": [318.4006289062594, 93.0, 0]}, {"t": 40, "s": [317.7184997872902, 173.94010767585027, 0]}, {"t": 50, "s": [304.340223923507, 265.7486121839514, 0]}, {"t": 60, "s": [311.2353564002575, 367.26406871192853, 0]}, {"t": 70, "s": [317.90620174215246, 477.6338310781814, 0]}, {"t": 80, "s": [302.9577573888669, 596.1972647421808, 0]}, {"t": 90, "s": [313.91799251701894, 722.4228634059948, 0]}, {"t": 100, "s": [303.00298455769854, 855.870929175277, 0]}, {"t": 110, "s": [312.9166611251766, 996.1698185319719, 0]}, {"t": 120, "s": [300.5558293537332, 1143.0, 0]}, {"t": 130, "s": [307.29429290521426, 1296.0828996529863, 0]}, {"t": 140, "s": [289.98334623630467, 1455.172829628501, 0]}, {"t": 150, "s": [293.57882988880965, 1620.0509831248423, 0]}, {"t": 160, "s": [302.1921724306317, 1790.5208614068022, 0]}, {"t": 170, "s": [286.50320764097324, 1966.4047214204743, 0]}, {"t": 180, "s": [289.90860381205687, 2147.5407685048604, 0]}]}, "r": {"a": 1, "k": [{"t": 0, "s": [0.0]}, {"t": 20, "s": [94.80725616634984]}, {"t": 40, "s": [189.6145123326997]}, {"t": 60, "s": [284.42176849904956]}, {"t": 80, "s": [379.2290246653994]}, {"t": 100, "s": [474.0362808317492]}, {"t": 120, "s": [568.8435369980991]}, {"t": 140, "s": [663.6507931644489]}, {"t": 160, "s": [758.4580493307988]}, {"t": 180, "s": [853.2653054971486]}]}, "s": {"a": 0, "k": [100, 100, 100]}}, "shapes": [{"ty": "gr", "it": [{"ty": "rc", "s": {"a": 0, "k": [8, 8]}, "p": {"a": 0, "k": [0, 0]}, "r": {"a": 0, "k": 2}}, {"ty": "fl", "c": {"a": 0, "k": [1, 1, 0, 1]}}]}]}, {"ty": 4, "nm": "Confetti_11", "ip": 0, "op": 180, "st": 0, "ks": {"o": {"a": 0, "k": 100}, "p": {"a": 1, "k": [{"t": 0, "s": [268.53114778318894, -185.0, 0]}, {"t": 10, "s": [275.8034031043466, -156.13248654051873, 0]}, {"t": 20, "s": [278.15735896823526, -103.3503419072274, 0]}, {"t": 30, "s": [282.7391308790776, -35.0, 0]}, {"t": 40, "s": [277.4244807773713, 45.94010767585027, 0]}, {"t": 50, "s": [289.2648725062478, 137.74861218395142, 0]}, {"t": 60, "s": [283.88504572479525, 239.26406871192853, 0]}, {"t": 70, "s": [299.92257215984836, 349.6338310781814, 0]}, {"t": 80, "s": [291.33268779877284, 468.1972647421808, 0]}, {"t": 90, "s": [289.9902366326124, 594.4228634059948, 0]}, {"t": 100, "s": [302.86465343166435, 727.870929175277, 0]}, {"t": 110, "s": [310.09955582673945, 868.1698185319719, 0]}, {"t": 120, "s": [303.67622814434185, 1015.0, 0]}, {"t": 130, "s": [311.45958018986653, 1168.0828996529863, 0]}, {"t": 140, "s": [314.73444579339065, 1327.172829628501, 0]}, {"t": 150, "s": [308.0085169197065, 1492.0509831248423, 0]}, {"t": 160, "s": [310.1529223969049, 1662.5208614068022, 0]}, {"t": 170, "s": [320.0660914704731, 1838.4047214204743, 0]}, {"t": 180, "s": [321.5707868275985, 2019.5407685048604, 0]}]}, "r": {"a": 1, "k": [{"t": 0, "s": [0.0]}, {"t": 20, "s": [52.15337934927794]}, {"t": 40, "s": [104.30675869855588]}, {"t": 60, "s": [156.46013804783382]}, {"t": 80, "s": [208.61351739711176]}, {"t": 100, "s": [260.7668967463897]}, {"t": 120, "s": [312.92027609566765]}, {"t": 140, "s": [365.0736554449456]}, {"t": 160, "s": [417.2270347942235]}, {"t": 180, "s": [469.3804141435014]}]}, "s": {"a": 0, "k": [100, 100, 100]}}, "shapes": [{"ty": "gr", "it": [{"ty": "rc", "s": {"a": 0, "k": [8, 8]}, "p": {"a": 0, "k": [0, 0]}, "r": {"a": 0, "k": 2}}, {"ty": "fl", "c": {"a": 0, "k": [1, 1, 0, 1]}}]}]}, {"ty": 4, "nm": "Confetti_10", "ip": 0, "op": 180, "st": 0, "ks": {"o": {"a": 0, "k": 100}, "p": {"a": 1, "k": [{"t": 0, "s": [289.78366482994915, -28.0, 0]}, {"t": 10, "s": [289.6808955309979, 0.8675134594812839, 0]}, {"t": 20, "s": [299.3590388556545, 53.6496580927726, 0]}, {"t": 30, "s": [299.6122644749783, 122.0, 0]}, {"t": 40, "s": [310.47181586077244, 202.94010767585027, 0]}, {"t": 50, "s": [312.9328493309566, 294.7486121839514, 0]}, {"t": 60, "s": [309.1518235643146, 396.26406871192853, 0]}, {"t": 70, "s": [313.0877316577272, 506.6338310781814, 0]}, {"t": 80, "s": [307.43751746137673, 625.1972647421808, 0]}, {"t": 90, "s": [316.59508912330017, 751.4228634059948, 0]}, {"t": 100, "s": [312.689723970201, 884.870929175277, 0]}, {"t": 110, "s": [325.29888551099134, 1025.169818531972, 0]}, {"t": 120, "s": [317.48872351352367, 1172.0, 0]}, {"t": 130, "s": [318.5915258044237, 1325.0828996529863, 0]}, {"t": 140, "s": [319.50508643048164, 1484.172829628501, 0]}, {"t": 150, "s": [327.757776656197, 1649.0509831248423, 0]}, {"t": 160, "s": [333.649098720301, 1819.5208614068022, 0]}, {"t": 170, "s": [344.41008862791944, 1995.4047214204743, 0]}, {"t": 180, "s": [342.2910995386011, 2176.5407685048604, 0]}]}, "r": {"a": 1, "k": [{"t": 0, "s": [0.0]}, {"t": 20, "s": [116.8423045359463]}, {"t": 40, "s": [233.6846090718926]}, {"t": 60, "s": [350.5269136078389]}, {"t": 80, "s": [467.3692181437852]}, {"t": 100, "s": [584.2115226797315]}, {"t": 120, "s": [701.0538272156778]}, {"t": 140, "s": [817.8961317516241]}, {"t": 160, "s": [934.7384362875704]}, {"t": 180, "s": [1051.5807408235166]}]}, "s": {"a": 0, "k": [100, 100, 100]}}, "shapes": [{"ty": "gr", "it": [{"ty": "rc", "s": {"a": 0, "k": [8, 8]}, "p": {"a": 0, "k": [0, 0]}, "r": {"a": 0, "k": 2}}, {"ty": "fl", "c": {"a": 0, "k": [0, 1, 0, 1]}}]}]}, {"ty": 4, "nm": "Confetti_9", "ip": 0, "op": 180, "st": 0, "ks": {"o": {"a": 0, "k": 100}, "p": {"a": 1, "k": [{"t": 0, "s": [315.6515098554091, -93.0, 0]}, {"t": 10, "s": [329.0747400149327, -64.13248654051871, 0]}, {"t": 20, "s": [324.2643839057948, -11.350341907227403, 0]}, {"t": 30, "s": [345.9408656975715, 57.0, 0]}, {"t": 40, "s": [359.90683439796925, 137.94010767585027, 0]}, {"t": 50, "s": [355.8628778451758, 229.74861218395142, 0]}, {"t": 60, "s": [361.18798497623527, 331.26406871192853, 0]}, {"t": 70, "s": [368.63740185841533, 441.6338310781814, 0]}, {"t": 80, "s": [377.28024015113215, 560.1972647421808, 0]}, {"t": 90, "s": [389.63135045912793, 686.4228634059948, 0]}, {"t": 100, "s": [396.8483982190854, 819.870929175277, 0]}, {"t": 110, "s": [413.11720044024054, 960.1698185319719, 0]}, {"t": 120, "s": [420.35772482627584, 1107.0, 0]}, {"t": 130, "s": [436.9428447760617, 1260.0828996529863, 0]}, {"t": 140, "s": [434.60311554428677, 1419.172829628501, 0]}, {"t": 150, "s": [442.44198285209615, 1584.0509831248423, 0]}, {"t": 160, "s": [451.5651563433162, 1754.5208614068022, 0]}, {"t": 170, "s": [469.65790803820687, 1930.4047214204743, 0]}, {"t": 180, "s": [478.92537280203834, 2111.5407685048604, 0]}]}, "r": {"a": 1, "k": [{"t": 0, "s": [0.0]}, {"t": 20, "s": [61.9535111189197]}, {"t": 40, "s": [123.9070222378394]}, {"t": 60, "s": [185.8605333567591]}, {"t": 80, "s": [247.8140444756788]}, {"t": 100, "s": [309.7675555945985]}, {"t": 120, "s": [371.7210667135182]}, {"t": 140, "s": [433.6745778324379]}, {"t": 160, "s": [495.6280889513576]}, {"t": 180, "s": [557.5816000702773]}]}, "s": {"a": 0, "k": [100, 100, 100]}}, "shapes": [{"ty": "gr", "it": [{"ty": "rc", "s": {"a": 0, "k": [8, 8]}, "p": {"a": 0, "k": [0, 0]}, "r": {"a": 0, "k": 2}}, {"ty": "fl", "c": {"a": 0, "k": [1, 1, 0, 1]}}]}]}, {"ty": 4, "nm": "Confetti_8", "ip": 0, "op": 180, "st": 0, "ks": {"o": {"a": 0, "k": 100}, "p": {"a": 1, "k": [{"t": 0, "s": [22.452967827059318, -200.0, 0]}, {"t": 10, "s": [31.244072580414375, -171.13248654051873, 0]}, {"t": 20, "s": [45.40118821802699, -118.3503419072274, 0]}, {"t": 30, "s": [60.30517986021738, -50.0, 0]}, {"t": 40, "s": [76.00628997339192, 30.94010767585027, 0]}, {"t": 50, "s": [98.20300101774633, 122.74861218395142, 0]}, {"t": 60, "s": [111.60952884139616, 224.26406871192853, 0]}, {"t": 70, "s": [119.20282514951504, 334.6338310781814, 0]}, {"t": 80, "s": [134.04200898746893, 453.1972647421808, 0]}, {"t": 90, "s": [159.4267206342926, 579.4228634059948, 0]}, {"t": 100, "s": [177.05154190686875, 712.870929175277, 0]}, {"t": 110, "s": [180.46122099569303, 853.1698185319719, 0]}, {"t": 120, "s": [198.29626239186317, 1000.0, 0]}, {"t": 130, "s": [207.50204060694116, 1153.0828996529863, 0]}, {"t": 140, "s": [232.29967342001265, 1312.172829628501, 0]}, {"t": 150, "s": [236.20463538535765, 1477.0509831248423, 0]}, {"t": 160, "s": [261.9252051758592, 1647.5208614068022, 0]}, {"t": 170, "s": [279.10440776854807, 1823.4047214204743, 0]}, {"t": 180, "s": [287.919951137869, 2004.5407685048604, 0]}]}, "r": {"a": 1, "k": [{"t": 0, "s": [0.0]}, {"t": 20, "s": [145.87848753911067]}, {"t": 40, "s": [291.75697507822133]}, {"t": 60, "s": [437.63546261733205]}, {"t": 80, "s": [583.5139501564427]}, {"t": 100, "s": [729.3924376955534]}, {"t": 120, "s": [875.2709252346641]}, {"t": 140, "s": [1021.1494127737748]}, {"t": 160, "s": [1167.0279003128853]}, {"t": 180, "s": [1312.9063878519962]}]}, "s": {"a": 0, "k": [100, 100, 100]}}, "shapes": [{"ty": "gr", "it": [{"ty": "rc", "s": {"a": 0, "k": [8, 8]}, "p": {"a": 0, "k": [0, 0]}, "r": {"a": 0, "k": 2}}, {"ty": "fl", "c": {"a": 0, "k": [1, 0, 1, 1]}}]}]}, {"ty": 4, "nm": "Confetti_7", "ip": 0, "op": 180, "st": 0, "ks": {"o": {"a": 0, "k": 100}, "p": {"a": 1, "k": [{"t": 0, "s": [148.2867052471127, -96.0, 0]}, {"t": 10, "s": [145.80469038049117, -67.13248654051871, 0]}, {"t": 20, "s": [151.43619079764613, -14.350341907227403, 0]}, {"t": 30, "s": [142.2113991531123, 54.0, 0]}, {"t": 40, "s": [155.1813607143702, 134.94010767585027, 0]}, {"t": 50, "s": [147.44579758835042, 226.74861218395142, 0]}, {"t": 60, "s": [144.08136818402375, 328.26406871192853, 0]}, {"t": 70, "s": [138.28340744305027, 438.6338310781814, 0]}, {"t": 80, "s": [136.94216689765324, 557.1972647421808, 0]}, {"t": 90, "s": [144.15395217749278, 683.4228634059948, 0]}, {"t": 100, "s": [147.19587693665125, 816.870929175277, 0]}, {"t": 110, "s": [142.00787652158536, 957.1698185319719, 0]}, {"t": 120, "s": [144.34492204113215, 1104.0, 0]}, {"t": 130, "s": [145.48727578720712, 1257.0828996529863, 0]}, {"t": 140, "s": [143.02551383946258, 1416.172829628501, 0]}, {"t": 150, "s": [149.7032091188266, 1581.0509831248423, 0]}, {"t": 160, "s": [136.66631661283355, 1751.5208614068022, 0]}, {"t": 170, "s": [147.5300964296595, 1927.4047214204743, 0]}, {"t": 180, "s": [132.87319586478768, 2108.5407685048604, 0]}]}, "r": {"a": 1, "k": [{"t": 0, "s": [0.0]}, {"t": 20, "s": [113.38047432066688]}, {"t": 40, "s": [226.76094864133375]}, {"t": 60, "s": [340.14142296200066]}, {"t": 80, "s": [453.5218972826675]}, {"t": 100, "s": [566.9023716033344]}, {"t": 120, "s": [680.2828459240013]}, {"t": 140, "s": [793.6633202446682]}, {"t": 160, "s": [907.043794565335]}, {"t": 180, "s": [1020.4242688860019]}]}, "s": {"a": 0, "k": [100, 100, 100]}}, "shapes": [{"ty": "gr", "it": [{"ty": "rc", "s": {"a": 0, "k": [8, 8]}, "p": {"a": 0, "k": [0, 0]}, "r": {"a": 0, "k": 2}}, {"ty": "fl", "c": {"a": 0, "k": [1, 0, 1, 1]}}]}]}, {"ty": 4, "nm": "Confetti_6", "ip": 0, "op": 180, "st": 0, "ks": {"o": {"a": 0, "k": 100}, "p": {"a": 1, "k": [{"t": 0, "s": [142.23815160536563, -24.0, 0]}, {"t": 10, "s": [146.2397259785685, 4.867513459481284, 0]}, {"t": 20, "s": [143.62808465544572, 57.6496580927726, 0]}, {"t": 30, "s": [159.2517577738809, 126.0, 0]}, {"t": 40, "s": [163.73430981335358, 206.94010767585027, 0]}, {"t": 50, "s": [150.89302234447467, 298.7486121839514, 0]}, {"t": 60, "s": [151.48143639803408, 400.26406871192853, 0]}, {"t": 70, "s": [163.49750705649546, 510.6338310781814, 0]}, {"t": 80, "s": [167.0249504767512, 629.1972647421808, 0]}, {"t": 90, "s": [155.56295286714382, 755.4228634059948, 0]}, {"t": 100, "s": [152.69551124539942, 888.870929175277, 0]}, {"t": 110, "s": [151.73602747605216, 1029.169818531972, 0]}, {"t": 120, "s": [156.93191747903137, 1176.0, 0]}, {"t": 130, "s": [163.04849019154804, 1329.0828996529863, 0]}, {"t": 140, "s": [160.45161612128967, 1488.172829628501, 0]}, {"t": 150, "s": [167.24419627756882, 1653.0509831248423, 0]}, {"t": 160, "s": [171.97385333649467, 1823.5208614068022, 0]}, {"t": 170, "s": [173.93064649815446, 1999.4047214204743, 0]}, {"t": 180, "s": [172.66937410184937, 2180.5407685048604, 0]}]}, "r": {"a": 1, "k": [{"t": 0, "s": [0.0]}, {"t": 20, "s": [194.63697682529562]}, {"t": 40, "s": [389.27395365059124]}, {"t": 60, "s": [583.9109304758869]}, {"t": 80, "s": [778.5479073011825]}, {"t": 100, "s": [973.1848841264782]}, {"t": 120, "s": [1167.8218609517737]}, {"t": 140, "s": [1362.4588377770694]}, {"t": 160, "s": [1557.095814602365]}, {"t": 180, "s": [1751.7327914276607]}]}, "s": {"a": 0, "k": [100, 100, 100]}}, "shapes": [{"ty": "gr", "it": [{"ty": "rc", "s": {"a": 0, "k": [8, 8]}, "p": {"a": 0, "k": [0, 0]}, "r": {"a": 0, "k": 2}}, {"ty": "fl", "c": {"a": 0, "k": [0, 0, 1, 1]}}]}]}, {"ty": 4, "nm": "Confetti_5", "ip": 0, "op": 180, "st": 0, "ks": {"o": {"a": 0, "k": 100}, "p": {"a": 1, "k": [{"t": 0, "s": [371.8888380536134, -114.0, 0]}, {"t": 10, "s": [362.11838484281697, -85.13248654051871, 0]}, {"t": 20, "s": [359.40205103851076, -32.3503419072274, 0]}, {"t": 30, "s": [351.4799180892133, 36.0, 0]}, {"t": 40, "s": [350.45410156674313, 116.94010767585027, 0]}, {"t": 50, "s": [359.6419489004117, 208.74861218395142, 0]}, {"t": 60, "s": [354.54836631374127, 310.26406871192853, 0]}, {"t": 70, "s": [360.4788644832742, 420.6338310781814, 0]}, {"t": 80, "s": [346.8182581834234, 539.1972647421808, 0]}, {"t": 90, "s": [364.15241173873864, 665.4228634059948, 0]}, {"t": 100, "s": [350.1655889199586, 798.870929175277, 0]}, {"t": 110, "s": [359.2138979167319, 939.1698185319719, 0]}, {"t": 120, "s": [348.4036387953233, 1086.0, 0]}, {"t": 130, "s": [359.06256558713966, 1239.0828996529863, 0]}, {"t": 140, "s": [346.7890003011254, 1398.172829628501, 0]}, {"t": 150, "s": [345.54608682138314, 1563.0509831248423, 0]}, {"t": 160, "s": [350.6331693569599, 1733.5208614068022, 0]}, {"t": 170, "s": [341.569282172803, 1909.4047214204743, 0]}, {"t": 180, "s": [358.8156022491284, 2090.5407685048604, 0]}]}, "r": {"a": 1, "k": [{"t": 0, "s": [0.0]}, {"t": 20, "s": [179.58415877349665]}, {"t": 40, "s": [359.1683175469933]}, {"t": 60, "s": [538.7524763204899]}, {"t": 80, "s": [718.3366350939866]}, {"t": 100, "s": [897.9207938674833]}, {"t": 120, "s": [1077.5049526409798]}, {"t": 140, "s": [1257.0891114144765]}, {"t": 160, "s": [1436.6732701879732]}, {"t": 180, "s": [1616.25742896147]}]}, "s": {"a": 0, "k": [100, 100, 100]}}, "shapes": [{"ty": "gr", "it": [{"ty": "rc", "s": {"a": 0, "k": [8, 8]}, "p": {"a": 0, "k": [0, 0]}, "r": {"a": 0, "k": 2}}, {"ty": "fl", "c": {"a": 0, "k": [0, 0, 1, 1]}}]}]}, {"ty": 4, "nm": "Confetti_4", "ip": 0, "op": 180, "st": 0, "ks": {"o": {"a": 0, "k": 100}, "p": {"a": 1, "k": [{"t": 0, "s": [120.90043573195967, -46.0, 0]}, {"t": 10, "s": [120.52125526219855, -17.132486540518716, 0]}, {"t": 20, "s": [96.79024689832772, 35.6496580927726, 0]}, {"t": 30, "s": [93.78966883632935, 104.0, 0]}, {"t": 40, "s": [79.04677643419281, 184.94010767585027, 0]}, {"t": 50, "s": [59.243920483108255, 276.7486121839514, 0]}, {"t": 60, "s": [32.855379277945225, 378.26406871192853, 0]}, {"t": 70, "s": [20.549649907345575, 488.6338310781814, 0]}, {"t": 80, "s": [4.525393785882947, 607.1972647421808, 0]}, {"t": 90, "s": [4.361632227786499, 733.4228634059948, 0]}, {"t": 100, "s": [-12.723750216372142, 866.870929175277, 0]}, {"t": 110, "s": [-36.6734221322899, 1007.1698185319719, 0]}, {"t": 120, "s": [-43.97915433710889, 1154.0, 0]}, {"t": 130, "s": [-53.91965982913707, 1307.0828996529863, 0]}, {"t": 140, "s": [-65.82749999591103, 1466.172829628501, 0]}, {"t": 150, "s": [-86.6272315042746, 1631.0509831248423, 0]}, {"t": 160, "s": [-98.8039872997686, 1801.5208614068022, 0]}, {"t": 170, "s": [-116.0561254016619, 1977.4047214204743, 0]}, {"t": 180, "s": [-135.47358545710048, 2158.5407685048604, 0]}]}, "r": {"a": 1, "k": [{"t": 0, "s": [0.0]}, {"t": 20, "s": [46.79128458972512]}, {"t": 40, "s": [93.58256917945025]}, {"t": 60, "s": [140.37385376917535]}, {"t": 80, "s": [187.1651383589005]}, {"t": 100, "s": [233.9564229486256]}, {"t": 120, "s": [280.7477075383507]}, {"t": 140, "s": [327.53899212807585]}, {"t": 160, "s": [374.330276717801]}, {"t": 180, "s": [421.12156130752606]}]}, "s": {"a": 0, "k": [100, 100, 100]}}, "shapes": [{"ty": "gr", "it": [{"ty": "rc", "s": {"a": 0, "k": [8, 8]}, "p": {"a": 0, "k": [0, 0]}, "r": {"a": 0, "k": 2}}, {"ty": "fl", "c": {"a": 0, "k": [1, 0, 1, 1]}}]}]}, {"ty": 4, "nm": "Confetti_3", "ip": 0, "op": 180, "st": 0, "ks": {"o": {"a": 0, "k": 100}, "p": {"a": 1, "k": [{"t": 0, "s": [29.110917761958007, -121.0, 0]}, {"t": 10, "s": [14.857389902641135, -92.13248654051871, 0]}, {"t": 20, "s": [6.172483615170361, -39.3503419072274, 0]}, {"t": 30, "s": [-24.4086596443503, 29.0, 0]}, {"t": 40, "s": [-40.93705784046051, 109.94010767585027, 0]}, {"t": 50, "s": [-46.97098131704379, 201.74861218395142, 0]}, {"t": 60, "s": [-64.5666796424201, 303.26406871192853, 0]}, {"t": 70, "s": [-72.48733479091473, 413.6338310781814, 0]}, {"t": 80, "s": [-85.11754246517626, 532.1972647421808, 0]}, {"t": 90, "s": [-104.07275646807369, 658.4228634059948, 0]}, {"t": 100, "s": [-119.46462481754267, 791.870929175277, 0]}, {"t": 110, "s": [-142.2763538035652, 932.1698185319719, 0]}, {"t": 120, "s": [-143.3599382269021, 1079.0, 0]}, {"t": 130, "s": [-166.30688389610674, 1232.0828996529863, 0]}, {"t": 140, "s": [-180.75215128939618, 1391.172829628501, 0]}, {"t": 150, "s": [-194.51219555166836, 1556.0509831248423, 0]}, {"t": 160, "s": [-209.60689906637865, 1726.5208614068022, 0]}, {"t": 170, "s": [-212.33425894938557, 1902.4047214204743, 0]}, {"t": 180, "s": [-242.82510629010994, 2083.5407685048604, 0]}]}, "r": {"a": 1, "k": [{"t": 0, "s": [0.0]}, {"t": 20, "s": [195.1553687071294]}, {"t": 40, "s": [390.3107374142588]}, {"t": 60, "s": [585.4661061213883]}, {"t": 80, "s": [780.6214748285176]}, {"t": 100, "s": [975.7768435356471]}, {"t": 120, "s": [1170.9322122427766]}, {"t": 140, "s": [1366.087580949906]}, {"t": 160, "s": [1561.2429496570353]}, {"t": 180, "s": [1756.3983183641649]}]}, "s": {"a": 0, "k": [100, 100, 100]}}, "shapes": [{"ty": "gr", "it": [{"ty": "rc", "s": {"a": 0, "k": [8, 8]}, "p": {"a": 0, "k": [0, 0]}, "r": {"a": 0, "k": 2}}, {"ty": "fl", "c": {"a": 0, "k": [1, 1, 0, 1]}}]}]}, {"ty": 4, "nm": "Confetti_2", "ip": 0, "op": 180, "st": 0, "ks": {"o": {"a": 0, "k": 100}, "p": {"a": 1, "k": [{"t": 0, "s": [257.9855182367103, -116.0, 0]}, {"t": 10, "s": [253.08267802791343, -87.13248654051871, 0]}, {"t": 20, "s": [238.84407586817434, -34.3503419072274, 0]}, {"t": 30, "s": [248.08646641845172, 34.0, 0]}, {"t": 40, "s": [248.08955358469603, 114.94010767585027, 0]}, {"t": 50, "s": [243.65472431686248, 206.74861218395142, 0]}, {"t": 60, "s": [231.7494169812195, 308.26406871192853, 0]}, {"t": 70, "s": [220.6748360376649, 418.6338310781814, 0]}, {"t": 80, "s": [233.22217670657295, 537.1972647421808, 0]}, {"t": 90, "s": [220.0330913571543, 663.4228634059948, 0]}, {"t": 100, "s": [212.56173156064634, 796.870929175277, 0]}, {"t": 110, "s": [222.25823750837196, 937.1698185319719, 0]}, {"t": 120, "s": [204.23001196186692, 1084.0, 0]}, {"t": 130, "s": [203.5084936998222, 1237.0828996529863, 0]}, {"t": 140, "s": [203.84023890387505, 1396.172829628501, 0]}, {"t": 150, "s": [191.3474550432026, 1561.0509831248423, 0]}, {"t": 160, "s": [192.64670618384875, 1731.5208614068022, 0]}, {"t": 170, "s": [187.55770866012818, 1907.4047214204743, 0]}, {"t": 180, "s": [193.8229590779717, 2088.5407685048604, 0]}]}, "r": {"a": 1, "k": [{"t": 0, "s": [0.0]}, {"t": 20, "s": [162.41355567458533]}, {"t": 40, "s": [324.82711134917065]}, {"t": 60, "s": [487.24066702375603]}, {"t": 80, "s": [649.6542226983413]}, {"t": 100, "s": [812.0677783729267]}, {"t": 120, "s": [974.4813340475121]}, {"t": 140, "s": [1136.8948897220973]}, {"t": 160, "s": [1299.3084453966826]}, {"t": 180, "s": [1461.722001071268]}]}, "s": {"a": 0, "k": [100, 100, 100]}}, "shapes": [{"ty": "gr", "it": [{"ty": "rc", "s": {"a": 0, "k": [8, 8]}, "p": {"a": 0, "k": [0, 0]}, "r": {"a": 0, "k": 2}}, {"ty": "fl", "c": {"a": 0, "k": [1, 0, 0, 1]}}]}]}, {"ty": 4, "nm": "Confetti_1", "ip": 0, "op": 180, "st": 0, "ks": {"o": {"a": 0, "k": 100}, "p": {"a": 1, "k": [{"t": 0, "s": [90.88586964006197, -53.0, 0]}, {"t": 10, "s": [90.71340847948926, -24.132486540518716, 0]}, {"t": 20, "s": [122.55372419445054, 28.649658092772597, 0]}, {"t": 30, "s": [131.98725594328465, 97.0, 0]}, {"t": 40, "s": [138.77765453564146, 177.94010767585027, 0]}, {"t": 50, "s": [151.90453494384087, 269.7486121839514, 0]}, {"t": 60, "s": [169.78518312226606, 371.26406871192853, 0]}, {"t": 70, "s": [186.7957006521234, 481.6338310781814, 0]}, {"t": 80, "s": [212.42338218933634, 600.1972647421808, 0]}, {"t": 90, "s": [213.46488889207984, 726.4228634059948, 0]}, {"t": 100, "s": [244.52073274100894, 859.870929175277, 0]}, {"t": 110, "s": [248.28934256958775, 1000.1698185319719, 0]}, {"t": 120, "s": [267.88835224267604, 1147.0, 0]}, {"t": 130, "s": [274.27891981488364, 1300.0828996529863, 0]}, {"t": 140, "s": [294.0038049129027, 1459.172829628501, 0]}, {"t": 150, "s": [311.36767944093344, 1624.0509831248423, 0]}, {"t": 160, "s": [333.1372398135034, 1794.5208614068022, 0]}, {"t": 170, "s": [345.194611374362, 1970.4047214204743, 0]}, {"t": 180, "s": [352.36873024416695, 2151.5407685048604, 0]}]}, "r": {"a": 1, "k": [{"t": 0, "s": [0.0]}, {"t": 20, "s": [154.3083281096468]}, {"t": 40, "s": [308.6166562192936]}, {"t": 60, "s": [462.92498432894035]}, {"t": 80, "s": [617.2333124385872]}, {"t": 100, "s": [771.541640548234]}, {"t": 120, "s": [925.8499686578807]}, {"t": 140, "s": [1080.1582967675276]}, {"t": 160, "s": [1234.4666248771744]}, {"t": 180, "s": [1388.774952986821]}]}, "s": {"a": 0, "k": [100, 100, 100]}}, "shapes": [{"ty": "gr", "it": [{"ty": "rc", "s": {"a": 0, "k": [8, 8]}, "p": {"a": 0, "k": [0, 0]}, "r": {"a": 0, "k": 2}}, {"ty": "fl", "c": {"a": 0, "k": [0, 1, 0, 1]}}]}]}, {"ty": 4, "nm": "Confetti_0", "ip": 0, "op": 180, "st": 0, "ks": {"o": {"a": 0, "k": 100}, "p": {"a": 1, "k": [{"t": 0, "s": [193.6865752749316, -150.0, 0]}, {"t": 10, "s": [200.83257952608793, -121.13248654051871, 0]}, {"t": 20, "s": [197.41283574322674, -68.3503419072274, 0]}, {"t": 30, "s": [206.12627236352753, 0.0, 0]}, {"t": 40, "s": [206.39119188993297, 80.94010767585027, 0]}, {"t": 50, "s": [199.01995505972098, 172.74861218395142, 0]}, {"t": 60, "s": [197.15240527414727, 274.26406871192853, 0]}, {"t": 70, "s": [200.28730626114606, 384.6338310781814, 0]}, {"t": 80, "s": [195.62772327907808, 503.1972647421808, 0]}, {"t": 90, "s": [207.45811811947075, 629.4228634059948, 0]}, {"t": 100, "s": [205.9038118983355, 762.870929175277, 0]}, {"t": 110, "s": [202.70621918292736, 903.1698185319719, 0]}, {"t": 120, "s": [211.5532497479376, 1050.0, 0]}, {"t": 130, "s": [209.15490478802553, 1203.0828996529863, 0]}, {"t": 140, "s": [216.47374257109087, 1362.172829628501, 0]}, {"t": 150, "s": [208.40375747997777, 1527.0509831248423, 0]}, {"t": 160, "s": [213.52126816959102, 1697.5208614068022, 0]}, {"t": 170, "s": [217.75050778226174, 1873.4047214204743, 0]}, {"t": 180, "s": [204.98599121922558, 2054.5407685048604, 0]}]}, "r": {"a": 1, "k": [{"t": 0, "s": [0.0]}, {"t": 20, "s": [41.043190430366764]}, {"t": 40, "s": [82.08638086073353]}, {"t": 60, "s": [123.1295712911003]}, {"t": 80, "s": [164.17276172146705]}, {"t": 100, "s": [205.21595215183385]}, {"t": 120, "s": [246.2591425822006]}, {"t": 140, "s": [287.3023330125674]}, {"t": 160, "s": [328.3455234429341]}, {"t": 180, "s": [369.3887138733009]}]}, "s": {"a": 0, "k": [100, 100, 100]}}, "shapes": [{"ty": "gr", "it": [{"ty": "rc", "s": {"a": 0, "k": [8, 8]}, "p": {"a": 0, "k": [0, 0]}, "r": {"a": 0, "k": 2}}, {"ty": "fl", "c": {"a": 0, "k": [0, 1, 0, 1]}}]}]}]}